esgcov/__cli__.py
esgcov/__init__.py
esgcov/_version.py
esgcov/conf/__init__.py
esgcov/conf/about/esgcov.yaml
esgcov/conf/pipe/load_dataframes.yaml
esgcov/conf/pipe/preprocessing_esg_coverage.yaml
esgcov/conf/pipe/preprocessing_esg_ratings.yaml
esgcov/conf/pipe/save_dataframes.yaml
esgcov/conf/pipe/test_preprocessing.yaml
esgcov/conf/pipeline/dataset_preprocessing.yaml
esgcov/conf/project/esgcov.yaml
esgcov/conf/task/datasets.yaml
esgcov/conf/workflow/datasets.yaml
esgcov/datasets/__init__.py
esgcov/datasets/preprocessing.py
esgcov/py.typed
esg_coverage-0.3.2.dist-info/LICENSE
esg_coverage-0.3.2.dist-info/METADATA
esg_coverage-0.3.2.dist-info/WHEEL
esg_coverage-0.3.2.dist-info/entry_points.txt
esg_coverage-0.3.2.dist-info/RECORD
