Metadata-Version: 2.1
Name: esg-coverage
Version: 0.3.2
Summary: The Role of Analyst Coverage in Translating ESG Ratings into Stock Performance
Home-page: https://esg-coverage.entelecheia.ai
License: MIT
Author: Young Joon Lee
Author-email: entelecheia@hotmail.com
Requires-Python: >=3.8.1,<3.12
Classifier: License :: OSI Approved :: MIT License
Classifier: Programming Language :: Python :: 3
Classifier: Programming Language :: Python :: 3.9
Classifier: Programming Language :: Python :: 3.10
Classifier: Programming Language :: Python :: 3.11
Requires-Dist: hyfi (>=1.12.5,<2.0.0)
Requires-Dist: tabulate (>=0.9.0,<0.10.0)
Project-URL: Repository, https://github.com/entelecheia/esg-coverage
